oyemi_mcp/__init__.py
oyemi_mcp/server.py
oyemi_mcp-0.1.0.dist-info/METADATA
oyemi_mcp-0.1.0.dist-info/WHEEL
oyemi_mcp-0.1.0.dist-info/entry_points.txt
oyemi_mcp-0.1.0.dist-info/RECORD
