Metadata-Version: 2.4
Name: oyemi-mcp
Version: 0.1.0
Summary: MCP Server for Oyemi semantic lexicon - deterministic word-to-code mapping with valence analysis
Project-URL: Homepage, https://grandnasser.com
Project-URL: Repository, https://github.com/Osseni94/oyemi-mcp
Project-URL: Documentation, https://grandnasser.com/docs/oyemi-mcp
Author-email: Kaossara Osseni <admin@grandnasser.com>
License-Expression: MIT
Keywords: ai-tools,anthropic,claude,mcp,model-context-protocol,nlp,oyemi,semantic-analysis,sentiment,valence,wordnet
Classifier: Development Status :: 4 - Beta
Classifier: Intended Audience :: Developers
Classifier: License :: OSI Approved :: MIT License
Classifier: Programming Language :: Python :: 3
Classifier: Programming Language :: Python :: 3.10
Classifier: Programming Language :: Python :: 3.11
Classifier: Programming Language :: Python :: 3.12
Classifier: Topic :: Scientific/Engineering :: Artificial Intelligence
Classifier: Topic :: Text Processing :: Linguistic
Requires-Python: >=3.10
Requires-Dist: mcp>=1.0.0
Requires-Dist: oyemi>=3.2.0
Provides-Extra: dev
Requires-Dist: pytest-asyncio>=0.21; extra == 'dev'
Requires-Dist: pytest>=7.0; extra == 'dev'
